GraphLab_Create-2.1.dist-info/DESCRIPTION.rst
GraphLab_Create-2.1.dist-info/METADATA
GraphLab_Create-2.1.dist-info/RECORD
GraphLab_Create-2.1.dist-info/WHEEL
GraphLab_Create-2.1.dist-info/metadata.json
GraphLab_Create-2.1.dist-info/top_level.txt
graphlab/__init__.py
graphlab/_gl_pickle.py
graphlab/_json.py
graphlab/_minipsutil.py
graphlab/aggregate.py
graphlab/dependencies.py
graphlab/extensions.py
graphlab/generic.py
graphlab/lib_BayesianOnlineChangepoint.dll
graphlab/lib_canvas_streaming.dll
graphlab/lib_dml_function_invokation.dll
graphlab/libadditional_sframe_utilities.dll
graphlab/libcontent_interpretation_extensions.dll
graphlab/libdictionary_transformation_extensions.dll
graphlab/libeay32.dll
graphlab/libgpu_count.dll
graphlab/libgrouped_sframe.dll
graphlab/libhdfs.so
graphlab/libiconv-2.dll
graphlab/libinternal_demo.dll
graphlab/libjson.dll
graphlab/libminipsutil.dll
graphlab/libmxnet.dll
graphlab/librandom_sframe_generation.dll
graphlab/libsodium-13.dll
graphlab/libssh2-1.dll
graphlab/libtimeseries.dll
graphlab/libunity_core_shared.dll
graphlab/libunity_prop_server.dll
graphlab/libunity_toolkits_shared.dll
graphlab/libwinpthread-1.dll
graphlab/libxgboost_extension.dll
graphlab/numpy.py
graphlab/numpy_loader.py
graphlab/product_key.py
graphlab/sys_util.py
graphlab/version_check.py
graphlab/version_info.py
graphlab/zlib1.dll
graphlab/_beta/__init__.py
graphlab/_beta/views/__init__.py
graphlab/_beta/views/_overview_app.py
graphlab/_beta/views/_sframe_base_view.py
graphlab/_beta/views/churn_predictor/__init__.py
graphlab/_beta/views/churn_predictor/description.py
graphlab/_beta/views/churn_predictor/evaluate.py
graphlab/_beta/views/churn_predictor/explore.py
graphlab/_beta/views/churn_predictor/util.py
graphlab/_beta/views/data/__init__.py
graphlab/_beta/views/data/table.py
graphlab/_beta/views/platform/__init__.py
graphlab/_beta/views/platform/_app.py
graphlab/_beta/views/platform/_httpresponse.py
graphlab/_beta/views/platform/_view.py
graphlab/_beta/views/platform/_view_markup.py
graphlab/_beta/views/platform/_view_server.py
graphlab/_beta/views/platform/layout/__init__.py
graphlab/_beta/views/platform/layout/_layout.py
